pycommence/__init__.py
pycommence/cursor.py
pycommence/exceptions.py
pycommence/filters.py
pycommence/pycmc_types.py
pycommence/pycommence.py
pycommence/resolvers.py
pycommence/wrapper/__init__.py
pycommence/wrapper/_icommence.py
pycommence/wrapper/cmc_wrapper.py
pycommence/wrapper/conversation_wrapper.py
pycommence/wrapper/cursor_wrapper.py
pycommence/wrapper/row_wrapper.py
pycommence-0.2.4.dist-info/WHEEL
pycommence-0.2.4.dist-info/METADATA
pycommence-0.2.4.dist-info/RECORD
