Metadata-Version: 2.3
Name: pycommence
Version: 0.2.4
Summary: wrapper for Commence Rm via pywin32
Author: PawRequest
Author-email: PawRequest <pycommence+pawrequest@users.noreply.github.com>
Requires-Dist: pywin32
Requires-Dist: loguru
Requires-Dist: pydantic
Requires-Dist: comtypes>=1.4.11
Requires-Python: >=3.13
Project-URL: Homepage, https://github.com/pawrequest/pycommence
